LICENSE
MANIFEST.in
README.rst
setup.py
jsondate/__init__.py
jsondate.egg-info/PKG-INFO
jsondate.egg-info/SOURCES.txt
jsondate.egg-info/dependency_links.txt
jsondate.egg-info/not-zip-safe
jsondate.egg-info/top_level.txt
tests/__init__.py
tests/test_jsondate.py